[
  {
    "Timestamp": 46184.53874738426,
    "Name": "Marsss",
    "Pot 1 Selection 1": "Argentina",
    "Pot 1 Selection 2": "Spain",
    "Pot 2 Selection": "Morocco",
    "Pot 3 Selection": "Egypt",
    "Dark Horse 1": "Egypt",
    "Dark Horse 2": "South Africa",
    "Best Player": "Messi",
    "Top Goal Scorer": "Mbappe",
    "Best Goalkeeper": "Alisson"
  },
  {
    "Timestamp": 46184.539966111115,
    "Name": "ELBOV",
    "Pot 1 Selection 1": "Spain",
    "Pot 1 Selection 2": "England",
    "Pot 2 Selection": "Morocco",
    "Pot 3 Selection": "Norway",
    "Dark Horse 1": "Norway",
    "Dark Horse 2": "Türkiye",
    "Best Player": "Mark mina",
    "Top Goal Scorer": "Mark mina",
    "Best Goalkeeper": "Mark mina"
  },
  {
    "Timestamp": 46184.54158635417,
    "Name": "Filo nagy",
    "Pot 1 Selection 1": "Argentina",
    "Pot 1 Selection 2": "Spain",
    "Pot 2 Selection": "Croatia",
    "Pot 3 Selection": "Egypt",
    "Dark Horse 1": "Ivory Coast",
    "Dark Horse 2": "Norway",
    "Best Player": "Messi",
    "Top Goal Scorer": "haaland",
    "Best Goalkeeper": "Emiliano martinez"
  },
  {
    "Timestamp": 46184.54224325232,
    "Name": "Matthew Amir",
    "Pot 1 Selection 1": "Spain",
    "Pot 1 Selection 2": "England",
    "Pot 2 Selection": "Japan",
    "Pot 3 Selection": "Egypt",
    "Dark Horse 1": "Algeria",
    "Dark Horse 2": "Norway",
    "Best Player": "Yamal",
    "Top Goal Scorer": "Kane",
    "Best Goalkeeper": "Pikford"
  },
  {
    "Timestamp": 46184.5430715625,
    "Name": "Bishoy ",
    "Pot 1 Selection 1": "Portugal",
    "Pot 1 Selection 2": "Brazil",
    "Pot 2 Selection": "Switzerland",
    "Pot 3 Selection": "Ivory Coast",
    "Dark Horse 1": "Egypt",
    "Dark Horse 2": "Algeria",
    "Best Player": "Ronaldo",
    "Top Goal Scorer": "Yamel yamal",
    "Best Goalkeeper": "D.costa"
  },
  {
    "Timestamp": 46184.54866908565,
    "Name": "John Magdy",
    "Pot 1 Selection 1": "Spain",
    "Pot 1 Selection 2": "France",
    "Pot 2 Selection": "Japan",
    "Pot 3 Selection": "Egypt",
    "Dark Horse 1": "Sweden",
    "Dark Horse 2": "Egypt",
    "Best Player": "Michael olise",
    "Top Goal Scorer": "Mbappe",
    "Best Goalkeeper": "David raya"
  },
  {
    "Timestamp": 46184.54913826389,
    "Name": "Peter Remon",
    "Pot 1 Selection 1": "Spain",
    "Pot 1 Selection 2": "England",
    "Pot 2 Selection": "Morocco",
    "Pot 3 Selection": "Ivory Coast",
    "Dark Horse 1": "Türkiye",
    "Dark Horse 2": "Saudi Arabia",
    "Best Player": "Lamine Yamal",
    "Top Goal Scorer": "Harry kane ",
    "Best Goalkeeper": "Juan Garcia "
  },
  {
    "Timestamp": 46184.553898680555,
    "Name": "Supertikha Mark",
    "Pot 1 Selection 1": "Portugal",
    "Pot 1 Selection 2": "Brazil",
    "Pot 2 Selection": "Switzerland",
    "Pot 3 Selection": "Norway",
    "Dark Horse 1": "Sweden",
    "Dark Horse 2": "Egypt",
    "Best Player": "Harry Kane ",
    "Top Goal Scorer": "Kylian mbappe",
    "Best Goalkeeper": "Mike Maignan "
  },
  {
    "Timestamp": 46184.58851538194,
    "Name": "Martin Tamer",
    "Pot 1 Selection 1": "France",
    "Pot 1 Selection 2": "Argentina",
    "Pot 2 Selection": "Morocco",
    "Pot 3 Selection": "Ivory Coast",
    "Dark Horse 1": "Egypt",
    "Dark Horse 2": "Tunisia",
    "Best Player": "Leo messi ",
    "Top Goal Scorer": "Mbappe ",
    "Best Goalkeeper": "Mostafa shobeir"
  },
  {
    "Timestamp": 46184.64766173611,
    "Name": "Jonathan tamer ",
    "Pot 1 Selection 1": "France",
    "Pot 1 Selection 2": "Argentina",
    "Pot 2 Selection": "Morocco",
    "Pot 3 Selection": "Egypt",
    "Dark Horse 1": "Algeria",
    "Dark Horse 2": "Australia",
    "Best Player": "Pedri",
    "Top Goal Scorer": "Mbappe",
    "Best Goalkeeper": "Martinez "
  },
  {
    "Timestamp": 46184.73779172453,
    "Name": "Elarion",
    "Pot 1 Selection 1": "Argentina",
    "Pot 1 Selection 2": "France",
    "Pot 2 Selection": "Japan",
    "Pot 3 Selection": "Norway",
    "Dark Horse 1": "Ghana",
    "Dark Horse 2": "Algeria",
    "Best Player": "Messi",
    "Top Goal Scorer": "Mbappé",
    "Best Goalkeeper": "Martinez"
  },
  {
    "Timestamp": 46184.78803892361,
    "Name": "Christina Raafat el gamdaa moot",
    "Pot 1 Selection 1": "Spain",
    "Pot 1 Selection 2": "France",
    "Pot 2 Selection": "Senegal",
    "Pot 3 Selection": "Tunisia",
    "Dark Horse 1": "Algeria",
    "Dark Horse 2": "Türkiye",
    "Best Player": "Haaland ",
    "Top Goal Scorer": "Mbappe",
    "Best Goalkeeper": "Alison becker"
  },
  {
    "Timestamp": 46184.83217751158,
    "Name": "Tony Medhat ",
    "Pot 1 Selection 1": "Spain",
    "Pot 1 Selection 2": "Portugal",
    "Pot 2 Selection": "Japan",
    "Pot 3 Selection": "Norway",
    "Dark Horse 1": "Norway",
    "Dark Horse 2": "Ivory Coast",
    "Best Player": "Yamal",
    "Top Goal Scorer": "Mbappe ",
    "Best Goalkeeper": "Raya"
  },
  {
    "Timestamp": 46184.85506181713,
    "Name": "Mina Ezzat (Keriakos)",
    "Pot 1 Selection 1": "Portugal",
    "Pot 1 Selection 2": "Brazil",
    "Pot 2 Selection": "Japan",
    "Pot 3 Selection": "Egypt",
    "Dark Horse 1": "Ivory Coast",
    "Dark Horse 2": "Algeria",
    "Best Player": "Cristiano Ronaldo",
    "Top Goal Scorer": "Kylian Mbappé",
    "Best Goalkeeper": "Juan Garcia"
  },
  {
    "Timestamp": 46184.87353040509,
    "Name": "Shady Karam",
    "Pot 1 Selection 1": "Spain",
    "Pot 1 Selection 2": "France",
    "Pot 2 Selection": "Croatia",
    "Pot 3 Selection": "Norway",
    "Dark Horse 1": "Norway",
    "Dark Horse 2": "Egypt",
    "Best Player": "Lamine Yamal",
    "Top Goal Scorer": "Mbappe ",
    "Best Goalkeeper": "Courtois"
  },
  {
    "Timestamp": 46184.89782179398,
    "Name": "Mark g",
    "Pot 1 Selection 1": "Spain",
    "Pot 1 Selection 2": "Netherlands",
    "Pot 2 Selection": "Morocco",
    "Pot 3 Selection": "Egypt",
    "Dark Horse 1": "Türkiye",
    "Dark Horse 2": "Ivory Coast",
    "Best Player": "Cr7",
    "Top Goal Scorer": "Cr7",
    "Best Goalkeeper": "شوبير "
  },
  {
    "Timestamp": 46184.967627777776,
    "Name": "Robbin Mourad",
    "Pot 1 Selection 1": "Portugal",
    "Pot 1 Selection 2": "France",
    "Pot 2 Selection": "Morocco",
    "Pot 3 Selection": "Egypt",
    "Dark Horse 1": "Egypt",
    "Dark Horse 2": "Ivory Coast",
    "Best Player": "Ronaldo",
    "Top Goal Scorer": "Ronaldo",
    "Best Goalkeeper": "courtois"
  },
  {
    "Timestamp": 46184.97122016204,
    "Name": "Bassel",
    "Pot 1 Selection 1": "Argentina",
    "Pot 1 Selection 2": "Spain",
    "Pot 2 Selection": "Japan",
    "Pot 3 Selection": "Egypt",
    "Dark Horse 1": "Sweden",
    "Dark Horse 2": "Australia",
    "Best Player": "Messi",
    "Top Goal Scorer": "Lamine yamal ",
    "Best Goalkeeper": "Unai Simon "
  },
  {
    "Timestamp": 46185.442633784725,
    "Name": "Mr Nebla",
    "Pot 1 Selection 1": "Brazil",
    "Pot 1 Selection 2": "Portugal",
    "Pot 2 Selection": "Colombia",
    "Pot 3 Selection": "Norway",
    "Dark Horse 1": "Türkiye",
    "Dark Horse 2": "Norway",
    "Best Player": "Bukayo Saka",
    "Top Goal Scorer": "Gyokeres",
    "Best Goalkeeper": "Raya"
  },
  {
    "Timestamp": 46185.63555287037,
    "Name": "Fr. Antonious",
    "Pot 1 Selection 1": "Spain",
    "Pot 1 Selection 2": "Brazil",
    "Pot 2 Selection": "Senegal",
    "Pot 3 Selection": "Algeria",
    "Dark Horse 1": "Algeria",
    "Dark Horse 2": "Ghana",
    "Best Player": "Lamen yamal ",
    "Top Goal Scorer": "Lamen yamal ",
    "Best Goalkeeper": "Alison baker "
  },
  {
    "Timestamp": 46185.6611399074,
    "Name": "Mina G. 😎",
    "Pot 1 Selection 1": "France",
    "Pot 1 Selection 2": "Spain",
    "Pot 2 Selection": "Colombia",
    "Pot 3 Selection": "Algeria",
    "Dark Horse 1": "Türkiye",
    "Dark Horse 2": "Paraguay",
    "Best Player": "Mbabe",
    "Top Goal Scorer": 6,
    "Best Goalkeeper": "France goal keeper ☺️"
  },
  {
    "Timestamp": 46185.67191934028,
    "Name": "Abo al phalaphel",
    "Pot 1 Selection 1": "Portugal",
    "Pot 1 Selection 2": "France",
    "Pot 2 Selection": "Japan",
    "Pot 3 Selection": "Norway",
    "Dark Horse 1": "Norway",
    "Dark Horse 2": "Egypt",
    "Best Player": "Mbappe",
    "Top Goal Scorer": "Cr7",
    "Best Goalkeeper": "Diego"
  },
  {
    "Timestamp": 46186.08263322916,
    "Name": "Filo Wafik",
    "Pot 1 Selection 1": "Spain",
    "Pot 1 Selection 2": "Argentina",
    "Pot 2 Selection": "Croatia",
    "Pot 3 Selection": "Norway",
    "Dark Horse 1": "Egypt",
    "Dark Horse 2": "Türkiye",
    "Best Player": "Mbappe",
    "Top Goal Scorer": "Mbappe",
    "Best Goalkeeper": "Martinez or alison"
  },
  {
    "Timestamp": 46186.948731400465,
    "Name": "Abouna Daniel",
    "Pot 1 Selection 1": "France",
    "Pot 1 Selection 2": "England",
    "Pot 2 Selection": "Switzerland",
    "Pot 3 Selection": "Egypt",
    "Dark Horse 1": "Czechia",
    "Dark Horse 2": "Sweden",
    "Best Player": "Mbappé ",
    "Top Goal Scorer": "Mbappé ",
    "Best Goalkeeper": "Allison backer"
  },
  {
    "Timestamp": 46190.91177543982,
    "Name": "YoussefOS",
    "Pot 1 Selection 1": "Argentina",
    "Pot 1 Selection 2": "England",
    "Pot 2 Selection": "Morocco",
    "Pot 3 Selection": "Norway",
    "Dark Horse 1": "Egypt",
    "Dark Horse 2": "Ivory Coast",
    "Best Player": "Messi",
    "Top Goal Scorer": "Mbappe",
    "Best Goalkeeper": "Martinez "
  }
]